[
  {
    "line": 1,
    "elements": [
      {
        "line": 2,
        "name": "Login into Application",
        "description": "",
        "id": "application-login;login-into-application",
        "type": "scenario",
        "keyword": "Scenario",
        "steps": [
          {
            "result": {
              "status": "undefined"
            },
            "line": 3,
            "name": "user click on login page",
            "match": {},
            "keyword": "Given "
          },
          {
            "result": {
              "status": "undefined"
            },
            "line": 4,
            "name": "user enter username password",
            "match": {},
            "keyword": "When "
          },
          {
            "result": {
              "status": "undefined"
            },
            "line": 5,
            "name": "user can see home page",
            "match": {},
            "keyword": "Then "
          }
        ]
      }
    ],
    "name": "Application login",
    "description": "",
    "id": "application-login",
    "keyword": "Feature",
    "uri": "C:/Users/Vaibhav/eclipse-workspace/Amazon order/src/Feature/dd.feature"
  }
]